src/__init__.py
src/cli.py
src/destroyer.py
src/generator.py
src/helper.py
src/sample/controller.txt
src/sample/helper.txt
src/template/__init__.py
src/template/app.py
src/template/database.py
src/template/requirements.txt
src/template/routes.py
src/template/static/css/style.css
src/template/templates/base.html
src/template/templates/index.html
flask_gem-1.2.dist-info/LICENSE
flask_gem-1.2.dist-info/METADATA
flask_gem-1.2.dist-info/WHEEL
flask_gem-1.2.dist-info/entry_points.txt
flask_gem-1.2.dist-info/RECORD
