Metadata-Version: 2.1
Name: flask-gem
Version: 1.2
Summary: Library for Generating Flask Applications in Rails-like Style
License: MIT
Keywords: Python,Flask,FlaskPython,FlaskWebFramework,FlaskWebDevelopment,CodeGeneration,FlaskDeveloperTools,FlaskRapidDevelopment,FlaskDevTools,scaffold,FlaskScaffold,FlaskAPIDevelopment,Instant App
Author: Sushmitha Popuri
Requires-Python: >=3.12,<4.0
Classifier: License :: OSI Approved :: MIT License
Classifier: Programming Language :: Python :: 3
Classifier: Programming Language :: Python :: 3.12
Requires-Dist: click (>=8.1.7,<9.0.0)
Requires-Dist: inflect (>=7.3.1,<8.0.0)
